{
  "schemaVersion": 1,
  "id": "ouo",
  "version": "${version}",

  "name": "With Task",
  "description": "Create your task!",
  "authors": [
    "Someoneice"
  ],
  "contact": {
    "homepage": "",
    "sources": ""
  },

  "license": "Pineapple",
  "icon": "logo.png",

  "environment": "*",
  "entrypoints": {
    "main": [
      "club.someoneice.ouo.MainKt::init"
    ]
  },
  "mixins": [
    "OUO.mixin.json"
  ],
  "depends": {
    "fabricloader": ">=0.8.7",
    "fabric": "*",
    "fabric-language-kotlin": "*",
    "minecraft": "*"
  },
  "suggests": {
    "flamingo": "*"
  }
}
